codex_mcp_http_bridge/__init__.py
codex_mcp_http_bridge/__main__.py
codex_mcp_http_bridge/config.py
codex_mcp_http_bridge/http_client.py
codex_mcp_http_bridge/stdio_server.py
codex_mcp_http_bridge-0.1.0.dist-info/licenses/LICENSE
codex_mcp_http_bridge-0.1.0.dist-info/METADATA
codex_mcp_http_bridge-0.1.0.dist-info/WHEEL
codex_mcp_http_bridge-0.1.0.dist-info/entry_points.txt
codex_mcp_http_bridge-0.1.0.dist-info/top_level.txt
codex_mcp_http_bridge-0.1.0.dist-info/RECORD
