Metadata-Version: 2.4
Name: codex-mcp-http-bridge
Version: 0.1.0
Summary: HTTP/OAuth bridge for connecting Codex to remote MCP servers
Author-email: GuruCloudAI <support@gurucloudai.com>
License: MIT
Project-URL: Homepage, https://github.com/gurucloudai/codex-mcp-http-bridge
Project-URL: Documentation, https://github.com/gurucloudai/codex-mcp-http-bridge#readme
Project-URL: Repository, https://github.com/gurucloudai/codex-mcp-http-bridge
Project-URL: Issues, https://github.com/gurucloudai/codex-mcp-http-bridge/issues
Keywords: mcp,model-context-protocol,codex,oauth,bridge,proxy
Classifier: Development Status :: 3 - Alpha
Classifier: Intended Audience :: Developers
Classifier: License :: OSI Approved :: MIT License
Classifier: Programming Language :: Python :: 3
Classifier: Programming Language :: Python :: 3.11
Classifier: Programming Language :: Python :: 3.12
Classifier: Topic :: Software Development :: Libraries :: Python Modules
Requires-Python: >=3.11
License-File: LICENSE
Requires-Dist: httpx>=0.27.0
Requires-Dist: pydantic>=2.0
Requires-Dist: pydantic-settings>=2.0
Requires-Dist: click>=8.1
Provides-Extra: dev
Requires-Dist: pytest>=7.0; extra == "dev"
Requires-Dist: pytest-asyncio>=0.21; extra == "dev"
Requires-Dist: pytest-cov>=4.0; extra == "dev"
Requires-Dist: black>=23.0; extra == "dev"
Requires-Dist: ruff>=0.1; extra == "dev"
Requires-Dist: mypy>=1.0; extra == "dev"
Dynamic: license-file
